{ provider: 'google',
  id: '100375807486385086020',
  displayName: 'Diego Burlando',
  name: { familyName: 'Burlando', givenName: 'Diego' },
  isPerson: true,
  isPlusUser: true,
  language: 'en',
  emails: [ { value: 'diego@dmm888.com', type: 'account' } ],
  email: 'diego@dmm888.com',
  gender: 'male',
  photos: [ { value: 'https://lh3.googleusercontent.com/-RiYAUJz9Rkk/AAAAAAAAAAI/AAAAAAAAACk/xmbv3yezWDU/photo.jpg?sz=50' } ],
  _raw: '{\n "kind": "plus#person",\n "etag": "\\"RqKWnRU4WW46-6W3rWhLR9iFZQM/DwwlT8oRwGQz9WxElNPeFd7tT04\\"",\n "gender": "male",\n "emails": [\n  {\n   "value": "diego@dmm888.com",\n   "type": "account"\n  }\n ],\n "objectType": "person",\n "id": "100375807486385086020",\n "displayName": "Diego Burlando",\n "name": {\n  "familyName": "Burlando",\n  "givenName": "Diego"\n },\n "url": "https://plus.google.com/100375807486385086020",\n "image": {\n  "url": "https://lh3.googleusercontent.com/-RiYAUJz9Rkk/AAAAAAAAAAI/AAAAAAAAACk/xmbv3yezWDU/photo.jpg?sz=50",\n  "isDefault": false\n },\n "isPlusUser": true,\n "language": "en",\n "ageRange": {\n  "min": 21\n },\n "circledByCount": 1,\n "verified": false\n}\n',
  _json: 
   { kind: 'plus#person',
     etag: '"RqKWnRU4WW46-6W3rWhLR9iFZQM/DwwlT8oRwGQz9WxElNPeFd7tT04"',
     gender: 'male',
     emails: [ [Object] ],
     objectType: 'person',
     id: '100375807486385086020',
     displayName: 'Diego Burlando',
     name: { familyName: 'Burlando', givenName: 'Diego' },
     url: 'https://plus.google.com/100375807486385086020',
     image: 
      { url: 'https://lh3.googleusercontent.com/-RiYAUJz9Rkk/AAAAAAAAAAI/AAAAAAAAACk/xmbv3yezWDU/photo.jpg?sz=50',
        isDefault: false },
     isPlusUser: true,
     language: 'en',
     ageRange: { min: 21 },
     circledByCount: 1,
     verified: false } }
